{
  "MSTU": {
    "symbol": "MSTU",
    "direction": "long",
    "quantity": 203,
    "entry_price": 4.05,
    "entry_time": "2026-06-15T09:39:59.333086-04:00",
    "stop_loss": 3.8446,
    "initial_stop_loss": 3.8446,
    "take_profit": 4.5808,
    "trailing_stop_pct": 0.01935256861365235,
    "is_penny_runner": true,
    "confidence": 0.75,
    "strategy": "momentum",
    "order_id": 974869,
    "executed_via": "IBKR",
    "max_hold_bars": 40,
    "bar_seconds": 300,
    "max_hold_days": 5,
    "scalp_mode": false,
    "same_candle_exit": false,
    "quick_scalp_pct": 0,
    "runner_pct": 0,
    "source": "",
    "breakout_play": false,
    "momentum_runner": false,
    "entry_type": "",
    "atr_value": 0,
    "size_multiplier": 1.0,
    "sector_heat": false,
    "prev_close": 0,
    "premarket_high": 4.05,
    "broker_stop_order_id": 974871,
    "broker_stop_price": 3.8446,
    "unrealized_pnl_pct": 0.004938271604938386,
    "current_price": 4.07,
    "_high_water_mark": 4.07
  },
  "RIOT": {
    "symbol": "RIOT",
    "direction": "long",
    "quantity": 59,
    "entry_price": 27.85,
    "entry_time": "2026-06-15T09:40:08.754661-04:00",
    "stop_loss": 27.063,
    "initial_stop_loss": 27.063,
    "take_profit": 29.573999999999998,
    "trailing_stop_pct": 0.015,
    "is_penny_runner": false,
    "confidence": 1.0,
    "strategy": "momentum",
    "order_id": 974895,
    "executed_via": "IBKR",
    "max_hold_bars": 40,
    "bar_seconds": 300,
    "max_hold_days": 5,
    "scalp_mode": false,
    "same_candle_exit": false,
    "quick_scalp_pct": 0,
    "runner_pct": 0,
    "source": "",
    "breakout_play": false,
    "momentum_runner": false,
    "entry_type": "",
    "atr_value": 0,
    "size_multiplier": 1.0,
    "sector_heat": false,
    "prev_close": 0,
    "premarket_high": 27.85,
    "broker_stop_order_id": 974897,
    "broker_stop_price": 27.063,
    "unrealized_pnl_pct": -0.016157989228007284,
    "current_price": 27.4,
    "_high_water_mark": 27.9
  },
  "XNDX": {
    "symbol": "XNDX",
    "direction": "long",
    "quantity": 72,
    "entry_price": 15.96,
    "entry_time": "2026-06-15T09:58:37.747821-04:00",
    "stop_loss": 15.294714285714285,
    "initial_stop_loss": 15.294714285714285,
    "take_profit": 17.88357142857143,
    "trailing_stop_pct": 0.023824423386375835,
    "is_penny_runner": false,
    "confidence": 0.65,
    "strategy": "momentum",
    "order_id": 976148,
    "executed_via": "IBKR",
    "max_hold_bars": 40,
    "bar_seconds": 300,
    "max_hold_days": 5,
    "scalp_mode": false,
    "same_candle_exit": false,
    "quick_scalp_pct": 0,
    "runner_pct": 0,
    "source": "",
    "breakout_play": false,
    "momentum_runner": false,
    "entry_type": "",
    "atr_value": 0,
    "size_multiplier": 1.0,
    "sector_heat": false,
    "prev_close": 0,
    "premarket_high": 15.96,
    "broker_stop_order_id": 976150,
    "broker_stop_price": 15.294714285714285,
    "unrealized_pnl_pct": -0.00438596491228072,
    "current_price": 15.89,
    "_high_water_mark": 16.06
  },
  "SPCX": {
    "symbol": "SPCX",
    "direction": "long",
    "quantity": 9,
    "entry_price": 172.96,
    "entry_time": "2026-06-15T10:19:49.835701-04:00",
    "stop_loss": 167.80457142857142,
    "initial_stop_loss": 167.80457142857142,
    "take_profit": 188.60285714285715,
    "trailing_stop_pct": 0.017647980085231264,
    "is_penny_runner": false,
    "confidence": 0.75,
    "strategy": "momentum",
    "order_id": 977607,
    "executed_via": "IBKR",
    "max_hold_bars": 40,
    "bar_seconds": 300,
    "max_hold_days": 5,
    "scalp_mode": false,
    "same_candle_exit": false,
    "quick_scalp_pct": 0,
    "runner_pct": 0,
    "source": "",
    "breakout_play": false,
    "momentum_runner": false,
    "entry_type": "",
    "atr_value": 0,
    "size_multiplier": 1.0,
    "sector_heat": false,
    "prev_close": 0,
    "premarket_high": 172.96,
    "broker_stop_order_id": 977609,
    "broker_stop_price": 167.80457142857142,
    "unrealized_pnl_pct": 0.0028330249768731535,
    "current_price": 173.45,
    "_high_water_mark": 173.97
  }
}