{
  "TRX-USD": {
    "symbol": "TRX-USD",
    "direction": "long",
    "quantity": 3193.53005,
    "entry_price": 0.3211,
    "entry_time": "2026-06-29T12:30:34.181361-04:00",
    "stop_loss": 0.30504499999999996,
    "initial_stop_loss": 0.30504499999999996,
    "take_profit": 0.3532100000000001,
    "trailing_stop_pct": 0.042,
    "is_penny_runner": false,
    "confidence": 0.6891521316576764,
    "strategy": "mean_reversion",
    "order_id": "tp_1782750634",
    "executed_via": "TradersPost",
    "max_hold_bars": 15,
    "bar_seconds": 300,
    "max_hold_days": 2,
    "scalp_mode": false,
    "same_candle_exit": false,
    "quick_scalp_pct": 0,
    "runner_pct": 0,
    "source": "",
    "breakout_play": false,
    "momentum_runner": false,
    "entry_type": "",
    "atr_value": 0,
    "size_multiplier": 1.0,
    "sector_heat": false,
    "prev_close": 0,
    "premarket_high": 0.3211,
    "broker_stop_order_id": null,
    "broker_stop_price": 0,
    "unrealized_pnl_pct": 0.0,
    "current_price": 0.3211
  }
}